marppy/__init__.py
marppy/marp.py
marppy-1.0.0.dist-info/LICENSE
marppy-1.0.0.dist-info/METADATA
marppy-1.0.0.dist-info/WHEEL
marppy-1.0.0.dist-info/entry_points.txt
marppy-1.0.0.dist-info/top_level.txt
marppy-1.0.0.dist-info/RECORD
