Metadata-Version: 2.1
Name: marppy
Version: 1.0.0
Summary: Convert to and from MARP coordinates
Home-page: https://github.com/amisr/marppy
Author: L. Lamarche, R. Varney, A. Reimer
Author-email: leslie.lamarche@sri.com
License: MIT License
Keywords: marp,apex,magnetic coordinates
Classifier: Programming Language :: Python :: 3
Classifier: Topic :: Scientific/Engineering
Classifier: Intended Audience :: Science/Research
Classifier: Natural Language :: English
Classifier: Programming Language :: Python
License-File: LICENSE
